{"cameraMode":{"drawMode":0,"name":"Shaded","section":"Shading Mode"},"sceneLighting":true,"audioPlay":false,"sceneViewState":{"showFog":true,"showMaterialUpdate":false,"showSkybox":true,"showFlares":true,"showImageEffects":true,"showParticleSystems":true},"in2DMode":false,"pivot":{"x":0.007834140211343766,"y":0.021936528384685518,"z":0.035077087581157687},"rotation":{"x":-0.08133646100759506,"y":0.9091601371765137,"z":-0.21155934035778047,"w":-0.34950459003448489},"size":0.04647926613688469,"orthographic":false}